setup.py
qiniuFolderSync/__init__.py
qiniuFolderSync/main.py
qiniuFolderSync/sync.py
qiniuFolderSync/utils.py
qiniuFolderSync.egg-info/PKG-INFO
qiniuFolderSync.egg-info/SOURCES.txt
qiniuFolderSync.egg-info/dependency_links.txt
qiniuFolderSync.egg-info/entry_points.txt
qiniuFolderSync.egg-info/not-zip-safe
qiniuFolderSync.egg-info/requires.txt
qiniuFolderSync.egg-info/top_level.txt