Metadata-Version: 1.0
Name: qiniuFolderSync
Version: 0.0.1
Summary: Sync local folder to qiniu bucket
Home-page: https://github.com/ipconfiger/qiniuFolderSync
Author: Alexander.Li
Author-email: superpowerlee@gmail.com
License: MIT License
Platform: UNKNOWN
